{
  "Windows_x64_schannel": [
    {
      "RttMs": 5,
      "BottleneckMbps": 5,
      "BottleneckBufferPackets": 1,
      "RandomLossDenominator": 0,
      "RandomReorderDenominator": 0,
      "ReorderDelayDeltaMs": 0,
      "Tcp": false,
      "DurationMs": 10000,
      "Pacing": false,
      "RateKbps": 332,
      "RawRateKbps": [
        327,
        334,
        336
      ]
    },
    {
      "RttMs": 5,
      "BottleneckMbps": 5,
      "BottleneckBufferPackets": 1,
      "RandomLossDenominator": 0,
      "RandomReorderDenominator": 0,
      "ReorderDelayDeltaMs": 0,
      "Tcp": false,
      "DurationMs": 10000,
      "Pacing": true,
      "RateKbps": 3582,
      "RawRateKbps": [
        3495,
        3652,
        3600
      ]
    },
    {
      "RttMs": 5,
      "BottleneckMbps": 5,
      "BottleneckBufferPackets": 2,
      "RandomLossDenominator": 0,
      "RandomReorderDenominator": 0,
      "ReorderDelayDeltaMs": 0,
      "Tcp": false,
      "DurationMs": 10000,
      "Pacing": false,
      "RateKbps": 3773,
      "RawRateKbps": [
        3754,
        3779,
        3785
      ]
    },
    {
      "RttMs": 5,
      "BottleneckMbps": 5,
      "BottleneckBufferPackets": 2,
      "RandomLossDenominator": 0,
      "RandomReorderDenominator": 0,
      "ReorderDelayDeltaMs": 0,
      "Tcp": false,
      "DurationMs": 10000,
      "Pacing": true,
      "RateKbps": 4582,
      "RawRateKbps": [
        4580,
        4583,
        4583
      ]
    },
    {
      "RttMs": 50,
      "BottleneckMbps": 5,
      "BottleneckBufferPackets": 6,
      "RandomLossDenominator": 0,
      "RandomReorderDenominator": 0,
      "ReorderDelayDeltaMs": 0,
      "Tcp": false,
      "DurationMs": 10000,
      "Pacing": false,
      "RateKbps": 4170,
      "RawRateKbps": [
        4181,
        4104,
        4224
      ]
    },
    {
      "RttMs": 50,
      "BottleneckMbps": 5,
      "BottleneckBufferPackets": 6,
      "RandomLossDenominator": 0,
      "RandomReorderDenominator": 0,
      "ReorderDelayDeltaMs": 0,
      "Tcp": false,
      "DurationMs": 10000,
      "Pacing": true,
      "RateKbps": 4394,
      "RawRateKbps": [
        4434,
        4405,
        4344
      ]
    },
    {
      "RttMs": 50,
      "BottleneckMbps": 5,
      "BottleneckBufferPackets": 23,
      "RandomLossDenominator": 0,
      "RandomReorderDenominator": 0,
      "ReorderDelayDeltaMs": 0,
      "Tcp": false,
      "DurationMs": 10000,
      "Pacing": false,
      "RateKbps": 4511,
      "RawRateKbps": [
        4520,
        4504,
        4509
      ]
    },
    {
      "RttMs": 50,
      "BottleneckMbps": 5,
      "BottleneckBufferPackets": 23,
      "RandomLossDenominator": 0,
      "RandomReorderDenominator": 0,
      "ReorderDelayDeltaMs": 0,
      "Tcp": false,
      "DurationMs": 10000,
      "Pacing": true,
      "RateKbps": 4561,
      "RawRateKbps": [
        4562,
        4571,
        4551
      ]
    },
    {
      "RttMs": 200,
      "BottleneckMbps": 5,
      "BottleneckBufferPackets": 23,
      "RandomLossDenominator": 0,
      "RandomReorderDenominator": 0,
      "ReorderDelayDeltaMs": 0,
      "Tcp": false,
      "DurationMs": 10000,
      "Pacing": false,
      "RateKbps": 2943,
      "RawRateKbps": [
        2653,
        3515,
        2661
      ]
    },
    {
      "RttMs": 200,
      "BottleneckMbps": 5,
      "BottleneckBufferPackets": 23,
      "RandomLossDenominator": 0,
      "RandomReorderDenominator": 0,
      "ReorderDelayDeltaMs": 0,
      "Tcp": false,
      "DurationMs": 10000,
      "Pacing": true,
      "RateKbps": 2961,
      "RawRateKbps": [
        3253,
        2575,
        3054
      ]
    },
    {
      "RttMs": 200,
      "BottleneckMbps": 5,
      "BottleneckBufferPackets": 92,
      "RandomLossDenominator": 0,
      "RandomReorderDenominator": 0,
      "ReorderDelayDeltaMs": 0,
      "Tcp": false,
      "DurationMs": 10000,
      "Pacing": false,
      "RateKbps": 4244,
      "RawRateKbps": [
        4244,
        4244,
        4245
      ]
    },
    {
      "RttMs": 200,
      "BottleneckMbps": 5,
      "BottleneckBufferPackets": 92,
      "RandomLossDenominator": 0,
      "RandomReorderDenominator": 0,
      "ReorderDelayDeltaMs": 0,
      "Tcp": false,
      "DurationMs": 10000,
      "Pacing": true,
      "RateKbps": 4248,
      "RawRateKbps": [
        4262,
        4230,
        4252
      ]
    },
    {
      "RttMs": 5,
      "BottleneckMbps": 30,
      "BottleneckBufferPackets": 3,
      "RandomLossDenominator": 0,
      "RandomReorderDenominator": 0,
      "ReorderDelayDeltaMs": 0,
      "Tcp": false,
      "DurationMs": 10000,
      "Pacing": false,
      "RateKbps": 5424,
      "RawRateKbps": [
        5446,
        5386,
        5440
      ]
    },
    {
      "RttMs": 5,
      "BottleneckMbps": 30,
      "BottleneckBufferPackets": 3,
      "RandomLossDenominator": 0,
      "RandomReorderDenominator": 0,
      "ReorderDelayDeltaMs": 0,
      "Tcp": false,
      "DurationMs": 10000,
      "Pacing": true,
      "RateKbps": 12040,
      "RawRateKbps": [
        12247,
        11935,
        11937
      ]
    },
    {
      "RttMs": 5,
      "BottleneckMbps": 30,
      "BottleneckBufferPackets": 14,
      "RandomLossDenominator": 0,
      "RandomReorderDenominator": 0,
      "ReorderDelayDeltaMs": 0,
      "Tcp": false,
      "DurationMs": 10000,
      "Pacing": false,
      "RateKbps": 27626,
      "RawRateKbps": [
        27511,
        27860,
        27506
      ]
    },
    {
      "RttMs": 5,
      "BottleneckMbps": 30,
      "BottleneckBufferPackets": 14,
      "RandomLossDenominator": 0,
      "RandomReorderDenominator": 0,
      "ReorderDelayDeltaMs": 0,
      "Tcp": false,
      "DurationMs": 10000,
      "Pacing": true,
      "RateKbps": 27871,
      "RawRateKbps": [
        27870,
        27864,
        27880
      ]
    },
    {
      "RttMs": 50,
      "BottleneckMbps": 30,
      "BottleneckBufferPackets": 34,
      "RandomLossDenominator": 0,
      "RandomReorderDenominator": 0,
      "ReorderDelayDeltaMs": 0,
      "Tcp": false,
      "DurationMs": 10000,
      "Pacing": false,
      "RateKbps": 11517,
      "RawRateKbps": [
        10135,
        9836,
        14579
      ]
    },
    {
      "RttMs": 50,
      "BottleneckMbps": 30,
      "BottleneckBufferPackets": 34,
      "RandomLossDenominator": 0,
      "RandomReorderDenominator": 0,
      "ReorderDelayDeltaMs": 0,
      "Tcp": false,
      "DurationMs": 10000,
      "Pacing": true,
      "RateKbps": 25555,
      "RawRateKbps": [
        23267,
        26692,
        26705
      ]
    },
    {
      "RttMs": 50,
      "BottleneckMbps": 30,
      "BottleneckBufferPackets": 138,
      "RandomLossDenominator": 0,
      "RandomReorderDenominator": 0,
      "ReorderDelayDeltaMs": 0,
      "Tcp": false,
      "DurationMs": 10000,
      "Pacing": false,
      "RateKbps": 27117,
      "RawRateKbps": [
        27095,
        27116,
        27140
      ]
    },
    {
      "RttMs": 50,
      "BottleneckMbps": 30,
      "BottleneckBufferPackets": 138,
      "RandomLossDenominator": 0,
      "RandomReorderDenominator": 0,
      "ReorderDelayDeltaMs": 0,
      "Tcp": false,
      "DurationMs": 10000,
      "Pacing": true,
      "RateKbps": 27169,
      "RawRateKbps": [
        27156,
        27175,
        27176
      ]
    },
    {
      "RttMs": 200,
      "BottleneckMbps": 30,
      "BottleneckBufferPackets": 138,
      "RandomLossDenominator": 0,
      "RandomReorderDenominator": 0,
      "ReorderDelayDeltaMs": 0,
      "Tcp": false,
      "DurationMs": 10000,
      "Pacing": false,
      "RateKbps": 23540,
      "RawRateKbps": [
        23652,
        23298,
        23669
      ]
    },
    {
      "RttMs": 200,
      "BottleneckMbps": 30,
      "BottleneckBufferPackets": 138,
      "RandomLossDenominator": 0,
      "RandomReorderDenominator": 0,
      "ReorderDelayDeltaMs": 0,
      "Tcp": false,
      "DurationMs": 10000,
      "Pacing": true,
      "RateKbps": 23843,
      "RawRateKbps": [
        23869,
        23842,
        23817
      ]
    },
    {
      "RttMs": 200,
      "BottleneckMbps": 30,
      "BottleneckBufferPackets": 550,
      "RandomLossDenominator": 0,
      "RandomReorderDenominator": 0,
      "ReorderDelayDeltaMs": 0,
      "Tcp": false,
      "DurationMs": 10000,
      "Pacing": false,
      "RateKbps": 24198,
      "RawRateKbps": [
        24207,
        24203,
        24184
      ]
    },
    {
      "RttMs": 200,
      "BottleneckMbps": 30,
      "BottleneckBufferPackets": 550,
      "RandomLossDenominator": 0,
      "RandomReorderDenominator": 0,
      "ReorderDelayDeltaMs": 0,
      "Tcp": false,
      "DurationMs": 10000,
      "Pacing": true,
      "RateKbps": 24290,
      "RawRateKbps": [
        24279,
        24295,
        24297
      ]
    },
    {
      "RttMs": 5,
      "BottleneckMbps": 100,
      "BottleneckBufferPackets": 11,
      "RandomLossDenominator": 0,
      "RandomReorderDenominator": 0,
      "ReorderDelayDeltaMs": 0,
      "Tcp": false,
      "DurationMs": 10000,
      "Pacing": false,
      "RateKbps": 22316,
      "RawRateKbps": [
        20804,
        23643,
        22500
      ]
    },
    {
      "RttMs": 5,
      "BottleneckMbps": 100,
      "BottleneckBufferPackets": 11,
      "RandomLossDenominator": 0,
      "RandomReorderDenominator": 0,
      "ReorderDelayDeltaMs": 0,
      "Tcp": false,
      "DurationMs": 10000,
      "Pacing": true,
      "RateKbps": 46841,
      "RawRateKbps": [
        48122,
        45235,
        47166
      ]
    },
    {
      "RttMs": 5,
      "BottleneckMbps": 100,
      "BottleneckBufferPackets": 46,
      "RandomLossDenominator": 0,
      "RandomReorderDenominator": 0,
      "ReorderDelayDeltaMs": 0,
      "Tcp": false,
      "DurationMs": 10000,
      "Pacing": false,
      "RateKbps": 92917,
      "RawRateKbps": [
        92937,
        92985,
        92828
      ]
    },
    {
      "RttMs": 5,
      "BottleneckMbps": 100,
      "BottleneckBufferPackets": 46,
      "RandomLossDenominator": 0,
      "RandomReorderDenominator": 0,
      "ReorderDelayDeltaMs": 0,
      "Tcp": false,
      "DurationMs": 10000,
      "Pacing": true,
      "RateKbps": 92916,
      "RawRateKbps": [
        92969,
        92899,
        92881
      ]
    },
    {
      "RttMs": 50,
      "BottleneckMbps": 100,
      "BottleneckBufferPackets": 115,
      "RandomLossDenominator": 0,
      "RandomReorderDenominator": 0,
      "ReorderDelayDeltaMs": 0,
      "Tcp": false,
      "DurationMs": 10000,
      "Pacing": false,
      "RateKbps": 81740,
      "RawRateKbps": [
        89052,
        67124,
        89045
      ]
    },
    {
      "RttMs": 50,
      "BottleneckMbps": 100,
      "BottleneckBufferPackets": 115,
      "RandomLossDenominator": 0,
      "RandomReorderDenominator": 0,
      "ReorderDelayDeltaMs": 0,
      "Tcp": false,
      "DurationMs": 10000,
      "Pacing": true,
      "RateKbps": 87155,
      "RawRateKbps": [
        87139,
        87273,
        87052
      ]
    },
    {
      "RttMs": 50,
      "BottleneckMbps": 100,
      "BottleneckBufferPackets": 458,
      "RandomLossDenominator": 0,
      "RandomReorderDenominator": 0,
      "ReorderDelayDeltaMs": 0,
      "Tcp": false,
      "DurationMs": 10000,
      "Pacing": false,
      "RateKbps": 89775,
      "RawRateKbps": [
        89721,
        89799,
        89804
      ]
    },
    {
      "RttMs": 50,
      "BottleneckMbps": 100,
      "BottleneckBufferPackets": 458,
      "RandomLossDenominator": 0,
      "RandomReorderDenominator": 0,
      "ReorderDelayDeltaMs": 0,
      "Tcp": false,
      "DurationMs": 10000,
      "Pacing": true,
      "RateKbps": 89752,
      "RawRateKbps": [
        89692,
        89844,
        89720
      ]
    },
    {
      "RttMs": 200,
      "BottleneckMbps": 100,
      "BottleneckBufferPackets": 458,
      "RandomLossDenominator": 0,
      "RandomReorderDenominator": 0,
      "ReorderDelayDeltaMs": 0,
      "Tcp": false,
      "DurationMs": 10000,
      "Pacing": false,
      "RateKbps": 54635,
      "RawRateKbps": [
        54568,
        54534,
        54802
      ]
    },
    {
      "RttMs": 200,
      "BottleneckMbps": 100,
      "BottleneckBufferPackets": 458,
      "RandomLossDenominator": 0,
      "RandomReorderDenominator": 0,
      "ReorderDelayDeltaMs": 0,
      "Tcp": false,
      "DurationMs": 10000,
      "Pacing": true,
      "RateKbps": 75568,
      "RawRateKbps": [
        76285,
        75313,
        75107
      ]
    },
    {
      "RttMs": 200,
      "BottleneckMbps": 100,
      "BottleneckBufferPackets": 1833,
      "RandomLossDenominator": 0,
      "RandomReorderDenominator": 0,
      "ReorderDelayDeltaMs": 0,
      "Tcp": false,
      "DurationMs": 10000,
      "Pacing": false,
      "RateKbps": 77841,
      "RawRateKbps": [
        77839,
        77875,
        77810
      ]
    },
    {
      "RttMs": 200,
      "BottleneckMbps": 100,
      "BottleneckBufferPackets": 1833,
      "RandomLossDenominator": 0,
      "RandomReorderDenominator": 0,
      "ReorderDelayDeltaMs": 0,
      "Tcp": false,
      "DurationMs": 10000,
      "Pacing": true,
      "RateKbps": 78127,
      "RawRateKbps": [
        78166,
        78052,
        78162
      ]
    }
  ]
}
