{
  "CommitHash": "b74029e",
  "Date": 1632422378000,
  "Tests": [
    {
      "PlatformName": "linux_x64_openssl",
      "TestName": "HPS",
      "MachineName": "0:TK5-3WP091209",
      "TputConfig": null,
      "RpsConfig": null,
      "HpsConfig": {},
      "Results": [
        12733.0,
        12491.0,
        12709.0,
        12744.0,
        12024.0
      ]
    },
    {
      "PlatformName": "linux_x64_openssl",
      "TestName": "RPS",
      "MachineName": "0:TK5-3WP091209",
      "TputConfig": null,
      "RpsConfig": {
        "ConnectionCount": 40,
        "RequestSize": 0,
        "ResponseSize": 4096,
        "ParallelRequests": 30
      },
      "HpsConfig": null,
      "Results": [
        132135.0,
        135025.0,
        138379.0,
        89617.0,
        143539.0
      ]
    },
    {
      "PlatformName": "linux_x64_openssl",
      "TestName": "RPS",
      "MachineName": "0:TK5-3WP091209",
      "TputConfig": null,
      "RpsConfig": {
        "ConnectionCount": 250,
        "RequestSize": 0,
        "ResponseSize": 4096,
        "ParallelRequests": 30
      },
      "HpsConfig": null,
      "Results": [
        480695.0,
        532594.0,
        521728.0,
        516892.0,
        416809.0
      ]
    },
    {
      "PlatformName": "linux_x64_openssl",
      "TestName": "RPS",
      "MachineName": "0:TK5-3WP091209",
      "TputConfig": null,
      "RpsConfig": {
        "ConnectionCount": 250,
        "RequestSize": 0,
        "ResponseSize": 0,
        "ParallelRequests": 30
      },
      "HpsConfig": null,
      "Results": [
        524433.0,
        721525.0,
        665394.0,
        509075.0,
        513369.0
      ]
    },
    {
      "PlatformName": "linux_x64_openssl",
      "TestName": "RPS",
      "MachineName": "0:TK5-3WP091209",
      "TputConfig": null,
      "RpsConfig": {
        "ConnectionCount": 250,
        "RequestSize": 0,
        "ResponseSize": 16384,
        "ParallelRequests": 30
      },
      "HpsConfig": null,
      "Results": [
        290124.0,
        285868.0,
        333036.0,
        309049.0,
        333213.0
      ]
    },
    {
      "PlatformName": "linux_x64_openssl",
      "TestName": "RPS",
      "MachineName": "0:TK5-3WP091209",
      "TputConfig": null,
      "RpsConfig": {
        "ConnectionCount": 250,
        "RequestSize": 0,
        "ResponseSize": 512,
        "ParallelRequests": 30
      },
      "HpsConfig": null,
      "Results": [
        664083.0,
        712265.0,
        508767.0,
        661551.0,
        646800.0
      ]
    },
    {
      "PlatformName": "linux_x64_openssl",
      "TestName": "Throughput",
      "MachineName": "0:TK5-3WP091209",
      "TputConfig": {
        "Loopback": true,
        "Encryption": true,
        "SendBuffering": false,
        "NumberOfStreams": 1,
        "ServerToClient": true
      },
      "RpsConfig": null,
      "HpsConfig": null,
      "Results": [
        3310914.0,
        4091785.0,
        3346957.0,
        3308701.0,
        3382073.0
      ]
    },
    {
      "PlatformName": "linux_x64_openssl",
      "TestName": "Throughput",
      "MachineName": "0:TK5-3WP091209",
      "TputConfig": {
        "Loopback": false,
        "Encryption": true,
        "SendBuffering": false,
        "NumberOfStreams": 1,
        "ServerToClient": true
      },
      "RpsConfig": null,
      "HpsConfig": null,
      "Results": [
        5729048.0,
        5727200.0,
        5579380.0,
        5784524.0,
        5800213.0
      ]
    },
    {
      "PlatformName": "linux_x64_openssl",
      "TestName": "Throughput",
      "MachineName": "0:TK5-3WP091209",
      "TputConfig": {
        "Loopback": true,
        "Encryption": false,
        "SendBuffering": false,
        "NumberOfStreams": 1,
        "ServerToClient": true
      },
      "RpsConfig": null,
      "HpsConfig": null,
      "Results": [
        6086524.0,
        6009987.0,
        6015037.0,
        6060034.0,
        6079514.0
      ]
    },
    {
      "PlatformName": "linux_x64_openssl",
      "TestName": "Throughput",
      "MachineName": "0:TK5-3WP091209",
      "TputConfig": {
        "Loopback": false,
        "Encryption": false,
        "SendBuffering": false,
        "NumberOfStreams": 1,
        "ServerToClient": true
      },
      "RpsConfig": null,
      "HpsConfig": null,
      "Results": [
        4988537.0,
        4963904.0,
        4971414.0,
        4968803.0,
        5787861.0
      ]
    },
    {
      "PlatformName": "linux_x64_openssl",
      "TestName": "Throughput",
      "MachineName": "0:TK5-3WP091209",
      "TputConfig": {
        "Loopback": true,
        "Encryption": true,
        "SendBuffering": false,
        "NumberOfStreams": 1,
        "ServerToClient": false
      },
      "RpsConfig": null,
      "HpsConfig": null,
      "Results": [
        2424077.0,
        2397622.0,
        2409401.0,
        2306398.0,
        2509783.0
      ]
    },
    {
      "PlatformName": "linux_x64_openssl",
      "TestName": "Throughput",
      "MachineName": "0:TK5-3WP091209",
      "TputConfig": {
        "Loopback": false,
        "Encryption": true,
        "SendBuffering": false,
        "NumberOfStreams": 1,
        "ServerToClient": false
      },
      "RpsConfig": null,
      "HpsConfig": null,
      "Results": [
        3740292.0,
        4264309.0,
        4160503.0,
        4154402.0,
        3852222.0
      ]
    },
    {
      "PlatformName": "linux_x64_openssl",
      "TestName": "Throughput",
      "MachineName": "0:TK5-3WP091209",
      "TputConfig": {
        "Loopback": true,
        "Encryption": false,
        "SendBuffering": false,
        "NumberOfStreams": 1,
        "ServerToClient": false
      },
      "RpsConfig": null,
      "HpsConfig": null,
      "Results": [
        1794774.0,
        1738476.0,
        1756372.0,
        1810512.0,
        1631824.0
      ]
    },
    {
      "PlatformName": "linux_x64_openssl",
      "TestName": "Throughput",
      "MachineName": "0:TK5-3WP091209",
      "TputConfig": {
        "Loopback": false,
        "Encryption": false,
        "SendBuffering": false,
        "NumberOfStreams": 1,
        "ServerToClient": false
      },
      "RpsConfig": null,
      "HpsConfig": null,
      "Results": [
        4166274.0,
        4088659.0,
        4225991.0,
        4072335.0,
        4242714.0
      ]
    },
    {
      "PlatformName": "linux_x64_openssl",
      "TestName": "Throughput",
      "MachineName": "0:TK5-3WP091209",
      "TputConfig": {
        "Loopback": true,
        "Encryption": true,
        "SendBuffering": true,
        "NumberOfStreams": 1,
        "ServerToClient": false
      },
      "RpsConfig": null,
      "HpsConfig": null,
      "Results": [
        2189461.0,
        2236771.0,
        2207897.0,
        2282144.0,
        2434189.0
      ]
    },
    {
      "PlatformName": "linux_x64_openssl",
      "TestName": "Throughput",
      "MachineName": "0:TK5-3WP091209",
      "TputConfig": {
        "Loopback": false,
        "Encryption": true,
        "SendBuffering": true,
        "NumberOfStreams": 1,
        "ServerToClient": false
      },
      "RpsConfig": null,
      "HpsConfig": null,
      "Results": [
        4736966.0,
        4633700.0,
        4742120.0,
        4640499.0,
        4553235.0
      ]
    },
    {
      "PlatformName": "Windows_x64_openssl",
      "TestName": "HPS",
      "MachineName": "22355:TK5-3WP09R0627",
      "TputConfig": null,
      "RpsConfig": null,
      "HpsConfig": {},
      "Results": [
        8310.0,
        8299.0,
        7510.0,
        7394.0,
        7718.0
      ]
    },
    {
      "PlatformName": "Windows_x64_openssl",
      "TestName": "RPS",
      "MachineName": "22355:TK5-3WP09R0627",
      "TputConfig": null,
      "RpsConfig": {
        "ConnectionCount": 40,
        "RequestSize": 0,
        "ResponseSize": 4096,
        "ParallelRequests": 30
      },
      "HpsConfig": null,
      "Results": [
        141107.0,
        143617.0,
        143522.0,
        146115.0,
        143836.0
      ]
    },
    {
      "PlatformName": "Windows_x64_openssl",
      "TestName": "RPS",
      "MachineName": "22355:TK5-3WP09R0627",
      "TputConfig": null,
      "RpsConfig": {
        "ConnectionCount": 250,
        "RequestSize": 0,
        "ResponseSize": 4096,
        "ParallelRequests": 30
      },
      "HpsConfig": null,
      "Results": [
        901568.0,
        885589.0,
        902349.0,
        1021463.0,
        964090.0
      ]
    },
    {
      "PlatformName": "Windows_x64_openssl",
      "TestName": "RPS",
      "MachineName": "22355:TK5-3WP09R0627",
      "TputConfig": null,
      "RpsConfig": {
        "ConnectionCount": 250,
        "RequestSize": 0,
        "ResponseSize": 0,
        "ParallelRequests": 30
      },
      "HpsConfig": null,
      "Results": [
        862233.0,
        869376.0,
        956711.0,
        774781.0,
        873333.0
      ]
    },
    {
      "PlatformName": "Windows_x64_openssl",
      "TestName": "RPS",
      "MachineName": "22355:TK5-3WP09R0627",
      "TputConfig": null,
      "RpsConfig": {
        "ConnectionCount": 250,
        "RequestSize": 0,
        "ResponseSize": 16384,
        "ParallelRequests": 30
      },
      "HpsConfig": null,
      "Results": [
        330350.0,
        352805.0,
        351859.0,
        352224.0,
        350197.0
      ]
    },
    {
      "PlatformName": "Windows_x64_openssl",
      "TestName": "RPS",
      "MachineName": "22355:TK5-3WP09R0627",
      "TputConfig": null,
      "RpsConfig": {
        "ConnectionCount": 250,
        "RequestSize": 0,
        "ResponseSize": 512,
        "ParallelRequests": 30
      },
      "HpsConfig": null,
      "Results": [
        771387.0,
        973178.0,
        870335.0,
        1005181.0,
        834817.0
      ]
    },
    {
      "PlatformName": "Windows_x64_openssl",
      "TestName": "TcpThroughput",
      "MachineName": "22355:TK5-3WP09R0627",
      "TputConfig": {
        "Loopback": true,
        "Encryption": false,
        "SendBuffering": false,
        "NumberOfStreams": 1,
        "ServerToClient": true
      },
      "RpsConfig": null,
      "HpsConfig": null,
      "Results": [
        8377551.0,
        8358932.0,
        8379117.0,
        8378103.0,
        8372207.0
      ]
    },
    {
      "PlatformName": "Windows_x64_openssl",
      "TestName": "TcpThroughput",
      "MachineName": "22355:TK5-3WP09R0627",
      "TputConfig": {
        "Loopback": false,
        "Encryption": false,
        "SendBuffering": false,
        "NumberOfStreams": 1,
        "ServerToClient": true
      },
      "RpsConfig": null,
      "HpsConfig": null,
      "Results": [
        11417374.0,
        8034508.0,
        11502822.0,
        8536114.0,
        11454925.0
      ]
    },
    {
      "PlatformName": "Windows_x64_openssl",
      "TestName": "TcpThroughput",
      "MachineName": "22355:TK5-3WP09R0627",
      "TputConfig": {
        "Loopback": true,
        "Encryption": false,
        "SendBuffering": false,
        "NumberOfStreams": 1,
        "ServerToClient": false
      },
      "RpsConfig": null,
      "HpsConfig": null,
      "Results": [
        8324683.0,
        8369794.0,
        8353207.0,
        8391281.0,
        8342040.0
      ]
    },
    {
      "PlatformName": "Windows_x64_openssl",
      "TestName": "TcpThroughput",
      "MachineName": "22355:TK5-3WP09R0627",
      "TputConfig": {
        "Loopback": false,
        "Encryption": false,
        "SendBuffering": false,
        "NumberOfStreams": 1,
        "ServerToClient": false
      },
      "RpsConfig": null,
      "HpsConfig": null,
      "Results": [
        9659380.0,
        9574566.0,
        11581379.0,
        9095327.0,
        9841224.0
      ]
    },
    {
      "PlatformName": "Windows_x64_openssl",
      "TestName": "Throughput",
      "MachineName": "22355:TK5-3WP09R0627",
      "TputConfig": {
        "Loopback": true,
        "Encryption": true,
        "SendBuffering": false,
        "NumberOfStreams": 1,
        "ServerToClient": true
      },
      "RpsConfig": null,
      "HpsConfig": null,
      "Results": [
        6008545.0,
        5946637.0,
        6032122.0,
        6046285.0,
        6047903.0
      ]
    },
    {
      "PlatformName": "Windows_x64_openssl",
      "TestName": "Throughput",
      "MachineName": "22355:TK5-3WP09R0627",
      "TputConfig": {
        "Loopback": false,
        "Encryption": true,
        "SendBuffering": false,
        "NumberOfStreams": 1,
        "ServerToClient": true
      },
      "RpsConfig": null,
      "HpsConfig": null,
      "Results": [
        6911700.0,
        6896667.0,
        6923319.0,
        5155845.0,
        6955723.0
      ]
    },
    {
      "PlatformName": "Windows_x64_openssl",
      "TestName": "Throughput",
      "MachineName": "22355:TK5-3WP09R0627",
      "TputConfig": {
        "Loopback": true,
        "Encryption": false,
        "SendBuffering": false,
        "NumberOfStreams": 1,
        "ServerToClient": true
      },
      "RpsConfig": null,
      "HpsConfig": null,
      "Results": [
        13208676.0,
        13250374.0,
        12706026.0,
        12946575.0,
        13106342.0
      ]
    },
    {
      "PlatformName": "Windows_x64_openssl",
      "TestName": "Throughput",
      "MachineName": "22355:TK5-3WP09R0627",
      "TputConfig": {
        "Loopback": false,
        "Encryption": false,
        "SendBuffering": false,
        "NumberOfStreams": 1,
        "ServerToClient": true
      },
      "RpsConfig": null,
      "HpsConfig": null,
      "Results": [
        17519980.0,
        17469423.0,
        17482574.0,
        12390431.0,
        17001074.0
      ]
    },
    {
      "PlatformName": "Windows_x64_openssl",
      "TestName": "Throughput",
      "MachineName": "22355:TK5-3WP09R0627",
      "TputConfig": {
        "Loopback": true,
        "Encryption": true,
        "SendBuffering": false,
        "NumberOfStreams": 1,
        "ServerToClient": false
      },
      "RpsConfig": null,
      "HpsConfig": null,
      "Results": [
        6099471.0,
        6071866.0,
        6087853.0,
        6064343.0,
        6096673.0
      ]
    },
    {
      "PlatformName": "Windows_x64_openssl",
      "TestName": "Throughput",
      "MachineName": "22355:TK5-3WP09R0627",
      "TputConfig": {
        "Loopback": false,
        "Encryption": true,
        "SendBuffering": false,
        "NumberOfStreams": 1,
        "ServerToClient": false
      },
      "RpsConfig": null,
      "HpsConfig": null,
      "Results": [
        6995740.0,
        7086491.0,
        7029938.0,
        7087953.0,
        7027400.0
      ]
    },
    {
      "PlatformName": "Windows_x64_openssl",
      "TestName": "Throughput",
      "MachineName": "22355:TK5-3WP09R0627",
      "TputConfig": {
        "Loopback": true,
        "Encryption": false,
        "SendBuffering": false,
        "NumberOfStreams": 1,
        "ServerToClient": false
      },
      "RpsConfig": null,
      "HpsConfig": null,
      "Results": [
        12986148.0,
        13450419.0,
        13502109.0,
        13198118.0,
        13269297.0
      ]
    },
    {
      "PlatformName": "Windows_x64_openssl",
      "TestName": "Throughput",
      "MachineName": "22355:TK5-3WP09R0627",
      "TputConfig": {
        "Loopback": false,
        "Encryption": false,
        "SendBuffering": false,
        "NumberOfStreams": 1,
        "ServerToClient": false
      },
      "RpsConfig": null,
      "HpsConfig": null,
      "Results": [
        8548118.0,
        8673167.0,
        8296095.0,
        8568094.0,
        8386192.0
      ]
    },
    {
      "PlatformName": "Windows_x64_openssl",
      "TestName": "Throughput",
      "MachineName": "22355:TK5-3WP09R0627",
      "TputConfig": {
        "Loopback": true,
        "Encryption": true,
        "SendBuffering": true,
        "NumberOfStreams": 1,
        "ServerToClient": false
      },
      "RpsConfig": null,
      "HpsConfig": null,
      "Results": [
        5419562.0,
        5300621.0,
        5345594.0,
        5272535.0,
        5305736.0
      ]
    },
    {
      "PlatformName": "Windows_x64_openssl",
      "TestName": "Throughput",
      "MachineName": "22355:TK5-3WP09R0627",
      "TputConfig": {
        "Loopback": false,
        "Encryption": true,
        "SendBuffering": true,
        "NumberOfStreams": 1,
        "ServerToClient": false
      },
      "RpsConfig": null,
      "HpsConfig": null,
      "Results": [
        6577900.0,
        6471913.0,
        6516706.0,
        6515111.0,
        6525312.0
      ]
    },
    {
      "PlatformName": "Windows_x64_schannel",
      "TestName": "HPS",
      "MachineName": "22355:TK5-3WP09R0629",
      "TputConfig": null,
      "RpsConfig": null,
      "HpsConfig": {},
      "Results": [
        8019.0,
        7980.0,
        7981.0,
        7978.0,
        7980.0
      ]
    },
    {
      "PlatformName": "Winkernel_x64_schannel",
      "TestName": "HPS",
      "MachineName": "22355:TK5-3WP09R0629",
      "TputConfig": null,
      "RpsConfig": null,
      "HpsConfig": {},
      "Results": [
        7897.0,
        7889.0,
        7904.0,
        7883.0,
        7869.0
      ]
    },
    {
      "PlatformName": "Windows_x64_schannel",
      "TestName": "RPS",
      "MachineName": "22355:TK5-3WP09R0629",
      "TputConfig": null,
      "RpsConfig": {
        "ConnectionCount": 40,
        "RequestSize": 0,
        "ResponseSize": 4096,
        "ParallelRequests": 30
      },
      "HpsConfig": null,
      "Results": [
        132733.0,
        131497.0,
        132231.0,
        131920.0,
        132378.0
      ]
    },
    {
      "PlatformName": "Windows_x64_schannel",
      "TestName": "RPS",
      "MachineName": "22355:TK5-3WP09R0629",
      "TputConfig": null,
      "RpsConfig": {
        "ConnectionCount": 250,
        "RequestSize": 0,
        "ResponseSize": 4096,
        "ParallelRequests": 30
      },
      "HpsConfig": null,
      "Results": [
        1031584.0,
        1055875.0,
        989574.0,
        1021789.0,
        977053.0
      ]
    },
    {
      "PlatformName": "Windows_x64_schannel",
      "TestName": "RPS",
      "MachineName": "22355:TK5-3WP09R0629",
      "TputConfig": null,
      "RpsConfig": {
        "ConnectionCount": 250,
        "RequestSize": 0,
        "ResponseSize": 0,
        "ParallelRequests": 30
      },
      "HpsConfig": null,
      "Results": [
        850697.0,
        1018754.0,
        810401.0,
        1277182.0,
        1061265.0
      ]
    },
    {
      "PlatformName": "Windows_x64_schannel",
      "TestName": "RPS",
      "MachineName": "22355:TK5-3WP09R0629",
      "TputConfig": null,
      "RpsConfig": {
        "ConnectionCount": 250,
        "RequestSize": 0,
        "ResponseSize": 16384,
        "ParallelRequests": 30
      },
      "HpsConfig": null,
      "Results": [
        346823.0,
        352245.0,
        352548.0,
        352778.0,
        352473.0
      ]
    },
    {
      "PlatformName": "Windows_x64_schannel",
      "TestName": "RPS",
      "MachineName": "22355:TK5-3WP09R0629",
      "TputConfig": null,
      "RpsConfig": {
        "ConnectionCount": 250,
        "RequestSize": 0,
        "ResponseSize": 512,
        "ParallelRequests": 30
      },
      "HpsConfig": null,
      "Results": [
        906575.0,
        1188254.0,
        1078478.0,
        1213915.0,
        1083824.0
      ]
    },
    {
      "PlatformName": "Winkernel_x64_schannel",
      "TestName": "RPS",
      "MachineName": "22355:TK5-3WP09R0629",
      "TputConfig": null,
      "RpsConfig": {
        "ConnectionCount": 40,
        "RequestSize": 0,
        "ResponseSize": 4096,
        "ParallelRequests": 30
      },
      "HpsConfig": null,
      "Results": [
        246634.0,
        249830.0,
        243230.0,
        250472.0,
        234030.0
      ]
    },
    {
      "PlatformName": "Winkernel_x64_schannel",
      "TestName": "RPS",
      "MachineName": "22355:TK5-3WP09R0629",
      "TputConfig": null,
      "RpsConfig": {
        "ConnectionCount": 250,
        "RequestSize": 0,
        "ResponseSize": 4096,
        "ParallelRequests": 30
      },
      "HpsConfig": null,
      "Results": [
        1065335.0,
        1116196.0,
        1063176.0,
        1030956.0,
        1053582.0
      ]
    },
    {
      "PlatformName": "Winkernel_x64_schannel",
      "TestName": "RPS",
      "MachineName": "22355:TK5-3WP09R0629",
      "TputConfig": null,
      "RpsConfig": {
        "ConnectionCount": 250,
        "RequestSize": 0,
        "ResponseSize": 0,
        "ParallelRequests": 30
      },
      "HpsConfig": null,
      "Results": [
        1043314.0,
        1184059.0,
        1182541.0,
        1105514.0,
        1267910.0
      ]
    },
    {
      "PlatformName": "Winkernel_x64_schannel",
      "TestName": "RPS",
      "MachineName": "22355:TK5-3WP09R0629",
      "TputConfig": null,
      "RpsConfig": {
        "ConnectionCount": 250,
        "RequestSize": 0,
        "ResponseSize": 16384,
        "ParallelRequests": 30
      },
      "HpsConfig": null,
      "Results": [
        136171.0,
        135503.0,
        147268.0,
        133787.0,
        147999.0
      ]
    },
    {
      "PlatformName": "Winkernel_x64_schannel",
      "TestName": "RPS",
      "MachineName": "22355:TK5-3WP09R0629",
      "TputConfig": null,
      "RpsConfig": {
        "ConnectionCount": 250,
        "RequestSize": 0,
        "ResponseSize": 512,
        "ParallelRequests": 30
      },
      "HpsConfig": null,
      "Results": [
        1074912.0,
        1189557.0,
        1314921.0,
        1172872.0,
        1153066.0
      ]
    },
    {
      "PlatformName": "Windows_x64_schannel",
      "TestName": "TcpThroughput",
      "MachineName": "22355:TK5-3WP09R0629",
      "TputConfig": {
        "Loopback": true,
        "Encryption": false,
        "SendBuffering": false,
        "NumberOfStreams": 1,
        "ServerToClient": true
      },
      "RpsConfig": null,
      "HpsConfig": null,
      "Results": [
        8303492.0,
        8339557.0,
        8325870.0,
        8319999.0,
        8308736.0
      ]
    },
    {
      "PlatformName": "Windows_x64_schannel",
      "TestName": "TcpThroughput",
      "MachineName": "22355:TK5-3WP09R0629",
      "TputConfig": {
        "Loopback": false,
        "Encryption": false,
        "SendBuffering": false,
        "NumberOfStreams": 1,
        "ServerToClient": true
      },
      "RpsConfig": null,
      "HpsConfig": null,
      "Results": [
        11630687.0,
        11586772.0,
        11001334.0,
        11684768.0,
        11671445.0
      ]
    },
    {
      "PlatformName": "Windows_x64_schannel",
      "TestName": "TcpThroughput",
      "MachineName": "22355:TK5-3WP09R0629",
      "TputConfig": {
        "Loopback": true,
        "Encryption": false,
        "SendBuffering": false,
        "NumberOfStreams": 1,
        "ServerToClient": false
      },
      "RpsConfig": null,
      "HpsConfig": null,
      "Results": [
        8321652.0,
        8342070.0,
        8350551.0,
        8344903.0,
        8371322.0
      ]
    },
    {
      "PlatformName": "Windows_x64_schannel",
      "TestName": "TcpThroughput",
      "MachineName": "22355:TK5-3WP09R0629",
      "TputConfig": {
        "Loopback": false,
        "Encryption": false,
        "SendBuffering": false,
        "NumberOfStreams": 1,
        "ServerToClient": false
      },
      "RpsConfig": null,
      "HpsConfig": null,
      "Results": [
        10250706.0,
        11554799.0,
        11486166.0,
        11594278.0,
        11538317.0
      ]
    },
    {
      "PlatformName": "Windows_x64_schannel",
      "TestName": "Throughput",
      "MachineName": "22355:TK5-3WP09R0629",
      "TputConfig": {
        "Loopback": true,
        "Encryption": true,
        "SendBuffering": false,
        "NumberOfStreams": 1,
        "ServerToClient": true
      },
      "RpsConfig": null,
      "HpsConfig": null,
      "Results": [
        7751119.0,
        7778072.0,
        7703429.0,
        7754688.0,
        7744478.0
      ]
    },
    {
      "PlatformName": "Windows_x64_schannel",
      "TestName": "Throughput",
      "MachineName": "22355:TK5-3WP09R0629",
      "TputConfig": {
        "Loopback": false,
        "Encryption": true,
        "SendBuffering": false,
        "NumberOfStreams": 1,
        "ServerToClient": true
      },
      "RpsConfig": null,
      "HpsConfig": null,
      "Results": [
        7980595.0,
        7585915.0,
        7698073.0,
        5230116.0,
        7334668.0
      ]
    },
    {
      "PlatformName": "Windows_x64_schannel",
      "TestName": "Throughput",
      "MachineName": "22355:TK5-3WP09R0629",
      "TputConfig": {
        "Loopback": true,
        "Encryption": false,
        "SendBuffering": false,
        "NumberOfStreams": 1,
        "ServerToClient": true
      },
      "RpsConfig": null,
      "HpsConfig": null,
      "Results": [
        19372758.0,
        19122629.0,
        19092942.0,
        19241777.0,
        19291170.0
      ]
    },
    {
      "PlatformName": "Windows_x64_schannel",
      "TestName": "Throughput",
      "MachineName": "22355:TK5-3WP09R0629",
      "TputConfig": {
        "Loopback": false,
        "Encryption": false,
        "SendBuffering": false,
        "NumberOfStreams": 1,
        "ServerToClient": true
      },
      "RpsConfig": null,
      "HpsConfig": null,
      "Results": [
        8542582.0,
        8742457.0,
        5478941.0,
        8463338.0,
        19564901.0
      ]
    },
    {
      "PlatformName": "Winkernel_x64_schannel",
      "TestName": "Throughput",
      "MachineName": "22355:TK5-3WP09R0629",
      "TputConfig": {
        "Loopback": false,
        "Encryption": true,
        "SendBuffering": false,
        "NumberOfStreams": 1,
        "ServerToClient": true
      },
      "RpsConfig": null,
      "HpsConfig": null,
      "Results": [
        6666763.0,
        6941398.0,
        7017088.0,
        6920181.0,
        6962748.0
      ]
    },
    {
      "PlatformName": "Winkernel_x64_schannel",
      "TestName": "Throughput",
      "MachineName": "22355:TK5-3WP09R0629",
      "TputConfig": {
        "Loopback": false,
        "Encryption": false,
        "SendBuffering": false,
        "NumberOfStreams": 1,
        "ServerToClient": true
      },
      "RpsConfig": null,
      "HpsConfig": null,
      "Results": [
        7708759.0,
        17545340.0,
        18446610.0,
        19227995.0,
        19494744.0
      ]
    },
    {
      "PlatformName": "Windows_x64_schannel",
      "TestName": "Throughput",
      "MachineName": "22355:TK5-3WP09R0629",
      "TputConfig": {
        "Loopback": true,
        "Encryption": true,
        "SendBuffering": false,
        "NumberOfStreams": 1,
        "ServerToClient": false
      },
      "RpsConfig": null,
      "HpsConfig": null,
      "Results": [
        7712408.0,
        7809933.0,
        7779705.0,
        7758102.0,
        7752182.0
      ]
    },
    {
      "PlatformName": "Windows_x64_schannel",
      "TestName": "Throughput",
      "MachineName": "22355:TK5-3WP09R0629",
      "TputConfig": {
        "Loopback": false,
        "Encryption": true,
        "SendBuffering": false,
        "NumberOfStreams": 1,
        "ServerToClient": false
      },
      "RpsConfig": null,
      "HpsConfig": null,
      "Results": [
        7743399.0,
        7735649.0,
        7813911.0,
        7528862.0,
        7623193.0
      ]
    },
    {
      "PlatformName": "Windows_x64_schannel",
      "TestName": "Throughput",
      "MachineName": "22355:TK5-3WP09R0629",
      "TputConfig": {
        "Loopback": true,
        "Encryption": false,
        "SendBuffering": false,
        "NumberOfStreams": 1,
        "ServerToClient": false
      },
      "RpsConfig": null,
      "HpsConfig": null,
      "Results": [
        18252296.0,
        18173330.0,
        17535572.0,
        18448971.0,
        17241936.0
      ]
    },
    {
      "PlatformName": "Windows_x64_schannel",
      "TestName": "Throughput",
      "MachineName": "22355:TK5-3WP09R0629",
      "TputConfig": {
        "Loopback": false,
        "Encryption": false,
        "SendBuffering": false,
        "NumberOfStreams": 1,
        "ServerToClient": false
      },
      "RpsConfig": null,
      "HpsConfig": null,
      "Results": [
        8180205.0,
        8237253.0,
        8837957.0,
        8565516.0,
        8306100.0
      ]
    },
    {
      "PlatformName": "Windows_x64_schannel",
      "TestName": "Throughput",
      "MachineName": "22355:TK5-3WP09R0629",
      "TputConfig": {
        "Loopback": true,
        "Encryption": true,
        "SendBuffering": true,
        "NumberOfStreams": 1,
        "ServerToClient": false
      },
      "RpsConfig": null,
      "HpsConfig": null,
      "Results": [
        7403523.0,
        6421929.0,
        6754480.0,
        5965319.0,
        6591957.0
      ]
    },
    {
      "PlatformName": "Windows_x64_schannel",
      "TestName": "Throughput",
      "MachineName": "22355:TK5-3WP09R0629",
      "TputConfig": {
        "Loopback": false,
        "Encryption": true,
        "SendBuffering": true,
        "NumberOfStreams": 1,
        "ServerToClient": false
      },
      "RpsConfig": null,
      "HpsConfig": null,
      "Results": [
        6456601.0,
        7206824.0,
        7211131.0,
        7120117.0,
        6203447.0
      ]
    },
    {
      "PlatformName": "Winkernel_x64_schannel",
      "TestName": "Throughput",
      "MachineName": "22355:TK5-3WP09R0629",
      "TputConfig": {
        "Loopback": false,
        "Encryption": true,
        "SendBuffering": false,
        "NumberOfStreams": 1,
        "ServerToClient": false
      },
      "RpsConfig": null,
      "HpsConfig": null,
      "Results": [
        5668024.0,
        6810382.0,
        6346501.0,
        6506117.0,
        6646734.0
      ]
    },
    {
      "PlatformName": "Winkernel_x64_schannel",
      "TestName": "Throughput",
      "MachineName": "22355:TK5-3WP09R0629",
      "TputConfig": {
        "Loopback": false,
        "Encryption": false,
        "SendBuffering": false,
        "NumberOfStreams": 1,
        "ServerToClient": false
      },
      "RpsConfig": null,
      "HpsConfig": null,
      "Results": [
        16381039.0,
        15341026.0,
        14561193.0,
        14432995.0,
        17920323.0
      ]
    },
    {
      "PlatformName": "Winkernel_x64_schannel",
      "TestName": "Throughput",
      "MachineName": "22355:TK5-3WP09R0629",
      "TputConfig": {
        "Loopback": false,
        "Encryption": true,
        "SendBuffering": true,
        "NumberOfStreams": 1,
        "ServerToClient": false
      },
      "RpsConfig": null,
      "HpsConfig": null,
      "Results": [
        6097788.0,
        5576117.0,
        5803018.0,
        5463904.0,
        6091548.0
      ]
    }
  ]
}
