{
  "CommitHash": "59d9add",
  "Date": 1599170810000,
  "Tests": [
    {
      "PlatformName": "Windows_x64_schannel",
      "TestName": "Throughput",
      "MachineName": "TK5-3WP09R0629",
      "TputConfig": {
        "Loopback": true,
        "Encryption": true,
        "SendBuffering": true,
        "NumberOfStreams": 1,
        "ServerToClient": false
      },
      "RpsConfig": null,
      "HpsConfig": null,
      "Results": [
        4198663.0,
        3853597.0,
        4274453.0,
        3766754.0,
        4324184.0,
        3887787.0,
        4349855.0,
        3842580.0,
        4273923.0,
        3788135.0
      ]
    },
    {
      "PlatformName": "Windows_x64_schannel",
      "TestName": "Throughput",
      "MachineName": "TK5-3WP09R0629",
      "TputConfig": {
        "Loopback": false,
        "Encryption": true,
        "SendBuffering": true,
        "NumberOfStreams": 1,
        "ServerToClient": false
      },
      "RpsConfig": null,
      "HpsConfig": null,
      "Results": [
        5214981.0,
        4938468.0,
        5209472.0,
        4933583.0,
        5212290.0,
        4972874.0,
        5229279.0,
        4917185.0,
        5249808.0,
        4889189.0
      ]
    },
    {
      "PlatformName": "Windows_x64_schannel",
      "TestName": "Throughput",
      "MachineName": "TK5-3WP09R0629",
      "TputConfig": {
        "Loopback": true,
        "Encryption": false,
        "SendBuffering": false,
        "NumberOfStreams": 1,
        "ServerToClient": false
      },
      "RpsConfig": null,
      "HpsConfig": null,
      "Results": [
        8735250.0,
        12116016.0,
        8842778.0,
        12973460.0,
        8761127.0,
        13125781.0,
        8843956.0,
        13369028.0,
        8938787.0,
        13354656.0
      ]
    },
    {
      "PlatformName": "Windows_x64_schannel",
      "TestName": "Throughput",
      "MachineName": "TK5-3WP09R0629",
      "TputConfig": {
        "Loopback": false,
        "Encryption": false,
        "SendBuffering": false,
        "NumberOfStreams": 1,
        "ServerToClient": false
      },
      "RpsConfig": null,
      "HpsConfig": null,
      "Results": [
        11131170.0,
        10030505.0,
        10780712.0,
        10933778.0,
        11053296.0,
        9698674.0,
        10992196.0,
        10554458.0,
        12164266.0,
        11100904.0
      ]
    },
    {
      "PlatformName": "Windows_x64_schannel",
      "TestName": "Throughput",
      "MachineName": "TK5-3WP09R0629",
      "TputConfig": {
        "Loopback": true,
        "Encryption": true,
        "SendBuffering": false,
        "NumberOfStreams": 1,
        "ServerToClient": false
      },
      "RpsConfig": null,
      "HpsConfig": null,
      "Results": [
        5391669.0,
        4569138.0,
        5334065.0,
        4700938.0,
        5377225.0,
        4659752.0,
        5356588.0,
        4717198.0,
        5380998.0,
        4603165.0
      ]
    },
    {
      "PlatformName": "Windows_x64_schannel",
      "TestName": "Throughput",
      "MachineName": "TK5-3WP09R0629",
      "TputConfig": {
        "Loopback": false,
        "Encryption": true,
        "SendBuffering": false,
        "NumberOfStreams": 1,
        "ServerToClient": false
      },
      "RpsConfig": null,
      "HpsConfig": null,
      "Results": [
        5888772.0,
        5876362.0,
        6068909.0,
        5855679.0,
        6063320.0,
        5943028.0,
        6084159.0,
        5936911.0,
        6099464.0,
        5976471.0
      ]
    },
    {
      "PlatformName": "Linux_x64_openssl",
      "TestName": "Throughput",
      "MachineName": "fv-az152",
      "TputConfig": {
        "Loopback": true,
        "Encryption": true,
        "SendBuffering": true,
        "NumberOfStreams": 1,
        "ServerToClient": false
      },
      "RpsConfig": null,
      "HpsConfig": null,
      "Results": [
        904645.0,
        908049.0,
        919834.0,
        940596.0,
        972319.0,
        896420.0,
        936675.0,
        893850.0,
        897323.0,
        908784.0
      ]
    },
    {
      "PlatformName": "Linux_x64_openssl",
      "TestName": "Throughput",
      "MachineName": "fv-az152",
      "TputConfig": {
        "Loopback": true,
        "Encryption": false,
        "SendBuffering": false,
        "NumberOfStreams": 1,
        "ServerToClient": false
      },
      "RpsConfig": null,
      "HpsConfig": null,
      "Results": [
        1318805.0,
        1175076.0,
        1348202.0,
        1155009.0,
        1281639.0,
        1330401.0,
        1166609.0,
        1198503.0,
        1141047.0,
        1435828.0
      ]
    },
    {
      "PlatformName": "Linux_x64_openssl",
      "TestName": "Throughput",
      "MachineName": "fv-az152",
      "TputConfig": {
        "Loopback": true,
        "Encryption": true,
        "SendBuffering": false,
        "NumberOfStreams": 1,
        "ServerToClient": false
      },
      "RpsConfig": null,
      "HpsConfig": null,
      "Results": [
        752596.0,
        704550.0,
        901642.0,
        929643.0,
        764062.0,
        943635.0,
        883689.0,
        889362.0,
        848626.0,
        801872.0
      ]
    },
    {
      "PlatformName": "Windows_x64_mitls",
      "TestName": "Throughput",
      "MachineName": "TK5-3WP09R0629",
      "TputConfig": {
        "Loopback": true,
        "Encryption": true,
        "SendBuffering": true,
        "NumberOfStreams": 1,
        "ServerToClient": false
      },
      "RpsConfig": null,
      "HpsConfig": null,
      "Results": [
        2017856.0,
        2154999.0,
        1968739.0,
        2138025.0,
        2010270.0,
        2127702.0,
        2013309.0,
        2127691.0,
        2009932.0,
        2133399.0
      ]
    },
    {
      "PlatformName": "Windows_x64_mitls",
      "TestName": "Throughput",
      "MachineName": "TK5-3WP09R0629",
      "TputConfig": {
        "Loopback": true,
        "Encryption": false,
        "SendBuffering": false,
        "NumberOfStreams": 1,
        "ServerToClient": false
      },
      "RpsConfig": null,
      "HpsConfig": null,
      "Results": [
        12667528.0,
        8883943.0,
        13172063.0,
        8882084.0,
        13098595.0,
        8833112.0,
        12602156.0,
        8646601.0,
        13185882.0,
        8877427.0
      ]
    },
    {
      "PlatformName": "Windows_x64_mitls",
      "TestName": "Throughput",
      "MachineName": "TK5-3WP09R0629",
      "TputConfig": {
        "Loopback": true,
        "Encryption": true,
        "SendBuffering": false,
        "NumberOfStreams": 1,
        "ServerToClient": false
      },
      "RpsConfig": null,
      "HpsConfig": null,
      "Results": [
        2212161.0,
        2382638.0,
        2205789.0,
        490923.0,
        2116111.0,
        2371077.0,
        2248221.0,
        2376595.0,
        2215896.0,
        2378086.0
      ]
    },
    {
      "PlatformName": "Windows_x64_openssl",
      "TestName": "Throughput",
      "MachineName": "TK5-3WP09R0629",
      "TputConfig": {
        "Loopback": true,
        "Encryption": true,
        "SendBuffering": true,
        "NumberOfStreams": 1,
        "ServerToClient": false
      },
      "RpsConfig": null,
      "HpsConfig": null,
      "Results": [
        1470032.0,
        1693613.0,
        1416596.0,
        1814668.0,
        1266490.0,
        1803382.0,
        1906348.0,
        1767550.0,
        1174534.0,
        1725694.0
      ]
    },
    {
      "PlatformName": "Windows_x64_openssl",
      "TestName": "Throughput",
      "MachineName": "TK5-3WP09R0629",
      "TputConfig": {
        "Loopback": true,
        "Encryption": false,
        "SendBuffering": false,
        "NumberOfStreams": 1,
        "ServerToClient": false
      },
      "RpsConfig": null,
      "HpsConfig": null,
      "Results": [
        8456404.0,
        12796703.0,
        8644452.0,
        12801751.0,
        8484390.0,
        12372830.0,
        8555769.0,
        12639179.0,
        8550840.0,
        12259399.0
      ]
    },
    {
      "PlatformName": "Windows_x64_openssl",
      "TestName": "Throughput",
      "MachineName": "TK5-3WP09R0629",
      "TputConfig": {
        "Loopback": true,
        "Encryption": true,
        "SendBuffering": false,
        "NumberOfStreams": 1,
        "ServerToClient": false
      },
      "RpsConfig": null,
      "HpsConfig": null,
      "Results": [
        1839185.0,
        2016124.0,
        2166826.0,
        2014273.0,
        2004652.0,
        2002492.0,
        2042414.0,
        1918663.0,
        2129292.0,
        2037442.0
      ]
    },
    {
      "PlatformName": "Windows_x64_schannel",
      "TestName": "RPS",
      "MachineName": "TK5-3WP09R0629",
      "TputConfig": null,
      "RpsConfig": {
        "ConnectionCount": 1000,
        "RequestSize": 0,
        "ResponseSize": 512,
        "ParallelRequests": 2
      },
      "HpsConfig": null,
      "Results": [
        672077.0,
        640609.0,
        674106.0,
        664242.0,
        666547.0
      ]
    },
    {
      "PlatformName": "Windows_x64_schannel",
      "TestName": "RPS",
      "MachineName": "TK5-3WP09R0629",
      "TputConfig": null,
      "RpsConfig": {
        "ConnectionCount": 1000,
        "RequestSize": 0,
        "ResponseSize": 16384,
        "ParallelRequests": 2
      },
      "HpsConfig": null,
      "Results": [
        319131.0,
        318801.0,
        323040.0,
        319126.0,
        320182.0
      ]
    },
    {
      "PlatformName": "Windows_x64_schannel",
      "TestName": "RPS",
      "MachineName": "TK5-3WP09R0629",
      "TputConfig": null,
      "RpsConfig": {
        "ConnectionCount": 1000,
        "RequestSize": 0,
        "ResponseSize": 0,
        "ParallelRequests": 2
      },
      "HpsConfig": null,
      "Results": [
        666245.0,
        661117.0,
        663460.0,
        682486.0,
        690766.0
      ]
    },
    {
      "PlatformName": "Windows_x64_schannel",
      "TestName": "RPS",
      "MachineName": "TK5-3WP09R0629",
      "TputConfig": null,
      "RpsConfig": {
        "ConnectionCount": 1000,
        "RequestSize": 0,
        "ResponseSize": 4096,
        "ParallelRequests": 2
      },
      "HpsConfig": null,
      "Results": [
        389408.0,
        402565.0,
        394262.0,
        397229.0,
        396145.0
      ]
    }
  ]
}
