{
  "CommitHash": "586141e",
  "Date": 1641951935000,
  "Tests": [
    {
      "PlatformName": "linux_x64_openssl",
      "TestName": "HPS",
      "MachineName": "0:TK5-3WP091209",
      "TputConfig": null,
      "RpsConfig": null,
      "HpsConfig": {},
      "Results": [
        12337.0,
        12245.0,
        12739.0,
        12500.0,
        12200.0
      ]
    },
    {
      "PlatformName": "linux_x64_openssl",
      "TestName": "RPS",
      "MachineName": "0:TK5-3WP091209",
      "TputConfig": null,
      "RpsConfig": {
        "ConnectionCount": 40,
        "RequestSize": 0,
        "ResponseSize": 4096,
        "ParallelRequests": 30
      },
      "HpsConfig": null,
      "Results": [
        141700.0,
        134501.0,
        139184.0,
        61461.0,
        92039.0
      ]
    },
    {
      "PlatformName": "linux_x64_openssl",
      "TestName": "RPS",
      "MachineName": "0:TK5-3WP091209",
      "TputConfig": null,
      "RpsConfig": {
        "ConnectionCount": 250,
        "RequestSize": 0,
        "ResponseSize": 4096,
        "ParallelRequests": 30
      },
      "HpsConfig": null,
      "Results": [
        489996.0,
        429864.0,
        418379.0,
        584646.0,
        470248.0
      ]
    },
    {
      "PlatformName": "linux_x64_openssl",
      "TestName": "RPS",
      "MachineName": "0:TK5-3WP091209",
      "TputConfig": null,
      "RpsConfig": {
        "ConnectionCount": 250,
        "RequestSize": 0,
        "ResponseSize": 0,
        "ParallelRequests": 30
      },
      "HpsConfig": null,
      "Results": [
        597658.0,
        637595.0,
        532442.0,
        635121.0,
        616012.0
      ]
    },
    {
      "PlatformName": "linux_x64_openssl",
      "TestName": "RPS",
      "MachineName": "0:TK5-3WP091209",
      "TputConfig": null,
      "RpsConfig": {
        "ConnectionCount": 250,
        "RequestSize": 0,
        "ResponseSize": 16384,
        "ParallelRequests": 30
      },
      "HpsConfig": null,
      "Results": [
        295300.0,
        323535.0,
        326315.0,
        329000.0,
        331842.0
      ]
    },
    {
      "PlatformName": "linux_x64_openssl",
      "TestName": "RPS",
      "MachineName": "0:TK5-3WP091209",
      "TputConfig": null,
      "RpsConfig": {
        "ConnectionCount": 250,
        "RequestSize": 0,
        "ResponseSize": 512,
        "ParallelRequests": 30
      },
      "HpsConfig": null,
      "Results": [
        621918.0,
        554888.0,
        520744.0,
        616233.0,
        524086.0
      ]
    },
    {
      "PlatformName": "linux_x64_openssl",
      "TestName": "Throughput",
      "MachineName": "0:TK5-3WP091209",
      "TputConfig": {
        "Loopback": true,
        "Encryption": true,
        "SendBuffering": false,
        "NumberOfStreams": 1,
        "ServerToClient": true
      },
      "RpsConfig": null,
      "HpsConfig": null,
      "Results": [
        3961470.0,
        3949089.0,
        4007246.0,
        3222801.0,
        3250056.0
      ]
    },
    {
      "PlatformName": "linux_x64_openssl",
      "TestName": "Throughput",
      "MachineName": "0:TK5-3WP091209",
      "TputConfig": {
        "Loopback": false,
        "Encryption": true,
        "SendBuffering": false,
        "NumberOfStreams": 1,
        "ServerToClient": true
      },
      "RpsConfig": null,
      "HpsConfig": null,
      "Results": [
        5114464.0,
        5485677.0,
        5685640.0,
        5114984.0,
        4881857.0
      ]
    },
    {
      "PlatformName": "linux_x64_openssl",
      "TestName": "Throughput",
      "MachineName": "0:TK5-3WP091209",
      "TputConfig": {
        "Loopback": true,
        "Encryption": false,
        "SendBuffering": false,
        "NumberOfStreams": 1,
        "ServerToClient": true
      },
      "RpsConfig": null,
      "HpsConfig": null,
      "Results": [
        4451351.0,
        4513972.0,
        4571985.0,
        4543346.0,
        4422428.0
      ]
    },
    {
      "PlatformName": "linux_x64_openssl",
      "TestName": "Throughput",
      "MachineName": "0:TK5-3WP091209",
      "TputConfig": {
        "Loopback": false,
        "Encryption": false,
        "SendBuffering": false,
        "NumberOfStreams": 1,
        "ServerToClient": true
      },
      "RpsConfig": null,
      "HpsConfig": null,
      "Results": [
        5041585.0,
        5816990.0,
        5693210.0,
        4678108.0,
        5583706.0
      ]
    },
    {
      "PlatformName": "linux_x64_openssl",
      "TestName": "Throughput",
      "MachineName": "0:TK5-3WP091209",
      "TputConfig": {
        "Loopback": true,
        "Encryption": true,
        "SendBuffering": false,
        "NumberOfStreams": 1,
        "ServerToClient": false
      },
      "RpsConfig": null,
      "HpsConfig": null,
      "Results": [
        2368173.0,
        2171209.0,
        2200775.0,
        2265225.0,
        2284341.0
      ]
    },
    {
      "PlatformName": "linux_x64_openssl",
      "TestName": "Throughput",
      "MachineName": "0:TK5-3WP091209",
      "TputConfig": {
        "Loopback": false,
        "Encryption": true,
        "SendBuffering": false,
        "NumberOfStreams": 1,
        "ServerToClient": false
      },
      "RpsConfig": null,
      "HpsConfig": null,
      "Results": [
        3863787.0,
        4738682.0,
        4648348.0,
        4612708.0,
        4739121.0
      ]
    },
    {
      "PlatformName": "linux_x64_openssl",
      "TestName": "Throughput",
      "MachineName": "0:TK5-3WP091209",
      "TputConfig": {
        "Loopback": true,
        "Encryption": false,
        "SendBuffering": false,
        "NumberOfStreams": 1,
        "ServerToClient": false
      },
      "RpsConfig": null,
      "HpsConfig": null,
      "Results": [
        1905824.0,
        1781117.0,
        1668353.0,
        2102830.0,
        1870595.0
      ]
    },
    {
      "PlatformName": "linux_x64_openssl",
      "TestName": "Throughput",
      "MachineName": "0:TK5-3WP091209",
      "TputConfig": {
        "Loopback": false,
        "Encryption": false,
        "SendBuffering": false,
        "NumberOfStreams": 1,
        "ServerToClient": false
      },
      "RpsConfig": null,
      "HpsConfig": null,
      "Results": [
        4179788.0,
        4339778.0,
        4401334.0,
        4404642.0,
        4369921.0
      ]
    },
    {
      "PlatformName": "linux_x64_openssl",
      "TestName": "Throughput",
      "MachineName": "0:TK5-3WP091209",
      "TputConfig": {
        "Loopback": true,
        "Encryption": true,
        "SendBuffering": true,
        "NumberOfStreams": 1,
        "ServerToClient": false
      },
      "RpsConfig": null,
      "HpsConfig": null,
      "Results": [
        2182858.0,
        2198011.0,
        2227192.0,
        2193067.0,
        2166927.0
      ]
    },
    {
      "PlatformName": "linux_x64_openssl",
      "TestName": "Throughput",
      "MachineName": "0:TK5-3WP091209",
      "TputConfig": {
        "Loopback": false,
        "Encryption": true,
        "SendBuffering": true,
        "NumberOfStreams": 1,
        "ServerToClient": false
      },
      "RpsConfig": null,
      "HpsConfig": null,
      "Results": [
        3849373.0,
        4777173.0,
        4727954.0,
        4636798.0,
        4695809.0
      ]
    },
    {
      "PlatformName": "Windows_x64_openssl",
      "TestName": "HPS",
      "MachineName": "22483:TK5-3WP09R0627",
      "TputConfig": null,
      "RpsConfig": null,
      "HpsConfig": {},
      "Results": [
        8132.0,
        7806.0,
        7652.0,
        8113.0,
        7635.0
      ]
    },
    {
      "PlatformName": "Windows_x64_openssl",
      "TestName": "RPS",
      "MachineName": "22483:TK5-3WP09R0627",
      "TputConfig": null,
      "RpsConfig": {
        "ConnectionCount": 40,
        "RequestSize": 0,
        "ResponseSize": 4096,
        "ParallelRequests": 30
      },
      "HpsConfig": null,
      "Results": [
        136241.0,
        136773.0,
        136512.0,
        132045.0,
        134657.0
      ]
    },
    {
      "PlatformName": "Windows_x64_openssl",
      "TestName": "RPS",
      "MachineName": "22483:TK5-3WP09R0627",
      "TputConfig": null,
      "RpsConfig": {
        "ConnectionCount": 250,
        "RequestSize": 0,
        "ResponseSize": 4096,
        "ParallelRequests": 30
      },
      "HpsConfig": null,
      "Results": [
        954927.0,
        861917.0,
        940331.0,
        928024.0,
        871009.0
      ]
    },
    {
      "PlatformName": "Windows_x64_openssl",
      "TestName": "RPS",
      "MachineName": "22483:TK5-3WP09R0627",
      "TputConfig": null,
      "RpsConfig": {
        "ConnectionCount": 250,
        "RequestSize": 0,
        "ResponseSize": 0,
        "ParallelRequests": 30
      },
      "HpsConfig": null,
      "Results": [
        872949.0,
        852356.0,
        829241.0,
        840237.0,
        811718.0
      ]
    },
    {
      "PlatformName": "Windows_x64_openssl",
      "TestName": "RPS",
      "MachineName": "22483:TK5-3WP09R0627",
      "TputConfig": null,
      "RpsConfig": {
        "ConnectionCount": 250,
        "RequestSize": 0,
        "ResponseSize": 16384,
        "ParallelRequests": 30
      },
      "HpsConfig": null,
      "Results": [
        336912.0,
        336206.0,
        350138.0,
        337685.0,
        335634.0
      ]
    },
    {
      "PlatformName": "Windows_x64_openssl",
      "TestName": "RPS",
      "MachineName": "22483:TK5-3WP09R0627",
      "TputConfig": null,
      "RpsConfig": {
        "ConnectionCount": 250,
        "RequestSize": 0,
        "ResponseSize": 512,
        "ParallelRequests": 30
      },
      "HpsConfig": null,
      "Results": [
        763446.0,
        820119.0,
        848483.0,
        856961.0,
        853585.0
      ]
    },
    {
      "PlatformName": "Windows_x64_openssl",
      "TestName": "TcpThroughput",
      "MachineName": "22483:TK5-3WP09R0627",
      "TputConfig": {
        "Loopback": true,
        "Encryption": false,
        "SendBuffering": false,
        "NumberOfStreams": 1,
        "ServerToClient": true
      },
      "RpsConfig": null,
      "HpsConfig": null,
      "Results": [
        8348586.0,
        8376700.0,
        8378410.0,
        8361116.0,
        8381110.0
      ]
    },
    {
      "PlatformName": "Windows_x64_openssl",
      "TestName": "TcpThroughput",
      "MachineName": "22483:TK5-3WP09R0627",
      "TputConfig": {
        "Loopback": false,
        "Encryption": false,
        "SendBuffering": false,
        "NumberOfStreams": 1,
        "ServerToClient": true
      },
      "RpsConfig": null,
      "HpsConfig": null,
      "Results": [
        11518954.0,
        12031857.0,
        11712867.0,
        11699506.0,
        11646985.0
      ]
    },
    {
      "PlatformName": "Windows_x64_openssl",
      "TestName": "TcpThroughput",
      "MachineName": "22483:TK5-3WP09R0627",
      "TputConfig": {
        "Loopback": true,
        "Encryption": false,
        "SendBuffering": false,
        "NumberOfStreams": 1,
        "ServerToClient": false
      },
      "RpsConfig": null,
      "HpsConfig": null,
      "Results": [
        8382559.0,
        8346213.0,
        8335130.0,
        8348029.0,
        8382585.0
      ]
    },
    {
      "PlatformName": "Windows_x64_openssl",
      "TestName": "TcpThroughput",
      "MachineName": "22483:TK5-3WP09R0627",
      "TputConfig": {
        "Loopback": false,
        "Encryption": false,
        "SendBuffering": false,
        "NumberOfStreams": 1,
        "ServerToClient": false
      },
      "RpsConfig": null,
      "HpsConfig": null,
      "Results": [
        9516428.0,
        9392024.0,
        9728348.0,
        10303887.0,
        9580253.0
      ]
    },
    {
      "PlatformName": "Windows_x64_openssl",
      "TestName": "Throughput",
      "MachineName": "22483:TK5-3WP09R0627",
      "TputConfig": {
        "Loopback": true,
        "Encryption": true,
        "SendBuffering": false,
        "NumberOfStreams": 1,
        "ServerToClient": true
      },
      "RpsConfig": null,
      "HpsConfig": null,
      "Results": [
        5845613.0,
        5876342.0,
        5962715.0,
        5882504.0,
        5915328.0
      ]
    },
    {
      "PlatformName": "Windows_x64_openssl",
      "TestName": "Throughput",
      "MachineName": "22483:TK5-3WP09R0627",
      "TputConfig": {
        "Loopback": false,
        "Encryption": true,
        "SendBuffering": false,
        "NumberOfStreams": 1,
        "ServerToClient": true
      },
      "RpsConfig": null,
      "HpsConfig": null,
      "Results": [
        6718694.0,
        6779135.0,
        6757567.0,
        6733986.0,
        6705480.0
      ]
    },
    {
      "PlatformName": "Windows_x64_openssl",
      "TestName": "Throughput",
      "MachineName": "22483:TK5-3WP09R0627",
      "TputConfig": {
        "Loopback": true,
        "Encryption": false,
        "SendBuffering": false,
        "NumberOfStreams": 1,
        "ServerToClient": true
      },
      "RpsConfig": null,
      "HpsConfig": null,
      "Results": [
        12663567.0,
        12597304.0,
        12570058.0,
        12491646.0,
        12671029.0
      ]
    },
    {
      "PlatformName": "Windows_x64_openssl",
      "TestName": "Throughput",
      "MachineName": "22483:TK5-3WP09R0627",
      "TputConfig": {
        "Loopback": false,
        "Encryption": false,
        "SendBuffering": false,
        "NumberOfStreams": 1,
        "ServerToClient": true
      },
      "RpsConfig": null,
      "HpsConfig": null,
      "Results": [
        13093257.0,
        17337501.0,
        16821653.0,
        16747332.0,
        16424052.0
      ]
    },
    {
      "PlatformName": "Windows_x64_openssl",
      "TestName": "Throughput",
      "MachineName": "22483:TK5-3WP09R0627",
      "TputConfig": {
        "Loopback": true,
        "Encryption": true,
        "SendBuffering": false,
        "NumberOfStreams": 1,
        "ServerToClient": false
      },
      "RpsConfig": null,
      "HpsConfig": null,
      "Results": [
        5836133.0,
        5854336.0,
        5814532.0,
        5973129.0,
        5792310.0
      ]
    },
    {
      "PlatformName": "Windows_x64_openssl",
      "TestName": "Throughput",
      "MachineName": "22483:TK5-3WP09R0627",
      "TputConfig": {
        "Loopback": false,
        "Encryption": true,
        "SendBuffering": false,
        "NumberOfStreams": 1,
        "ServerToClient": false
      },
      "RpsConfig": null,
      "HpsConfig": null,
      "Results": [
        6802235.0,
        6845060.0,
        6913752.0,
        6830545.0,
        6857434.0
      ]
    },
    {
      "PlatformName": "Windows_x64_openssl",
      "TestName": "Throughput",
      "MachineName": "22483:TK5-3WP09R0627",
      "TputConfig": {
        "Loopback": true,
        "Encryption": false,
        "SendBuffering": false,
        "NumberOfStreams": 1,
        "ServerToClient": false
      },
      "RpsConfig": null,
      "HpsConfig": null,
      "Results": [
        12862739.0,
        12743266.0,
        12961615.0,
        12721968.0,
        12820256.0
      ]
    },
    {
      "PlatformName": "Windows_x64_openssl",
      "TestName": "Throughput",
      "MachineName": "22483:TK5-3WP09R0627",
      "TputConfig": {
        "Loopback": false,
        "Encryption": false,
        "SendBuffering": false,
        "NumberOfStreams": 1,
        "ServerToClient": false
      },
      "RpsConfig": null,
      "HpsConfig": null,
      "Results": [
        9051990.0,
        8709160.0,
        9048130.0,
        8721789.0,
        8369225.0
      ]
    },
    {
      "PlatformName": "Windows_x64_openssl",
      "TestName": "Throughput",
      "MachineName": "22483:TK5-3WP09R0627",
      "TputConfig": {
        "Loopback": true,
        "Encryption": true,
        "SendBuffering": true,
        "NumberOfStreams": 1,
        "ServerToClient": false
      },
      "RpsConfig": null,
      "HpsConfig": null,
      "Results": [
        5509344.0,
        5223635.0,
        5231678.0,
        5175893.0,
        5386826.0
      ]
    },
    {
      "PlatformName": "Windows_x64_openssl",
      "TestName": "Throughput",
      "MachineName": "22483:TK5-3WP09R0627",
      "TputConfig": {
        "Loopback": false,
        "Encryption": true,
        "SendBuffering": true,
        "NumberOfStreams": 1,
        "ServerToClient": false
      },
      "RpsConfig": null,
      "HpsConfig": null,
      "Results": [
        6318406.0,
        6308807.0,
        5634328.0,
        6167314.0,
        6254659.0
      ]
    },
    {
      "PlatformName": "Windows_x64_schannel",
      "TestName": "HPS",
      "MachineName": "22483:TK5-3WP09R0627",
      "TputConfig": null,
      "RpsConfig": null,
      "HpsConfig": {},
      "Results": [
        10311.0,
        8644.0,
        8215.0,
        7328.0,
        7737.0
      ]
    },
    {
      "PlatformName": "Winkernel_x64_schannel",
      "TestName": "HPS",
      "MachineName": "22483:TK5-3WP09R0627",
      "TputConfig": null,
      "RpsConfig": null,
      "HpsConfig": {},
      "Results": [
        11318.0,
        11347.0,
        11423.0,
        11413.0,
        11273.0
      ]
    },
    {
      "PlatformName": "Windows_x64_schannel",
      "TestName": "RPS",
      "MachineName": "22483:TK5-3WP09R0627",
      "TputConfig": null,
      "RpsConfig": {
        "ConnectionCount": 40,
        "RequestSize": 0,
        "ResponseSize": 4096,
        "ParallelRequests": 30
      },
      "HpsConfig": null,
      "Results": [
        123819.0,
        123568.0,
        126167.0,
        124531.0,
        123788.0
      ]
    },
    {
      "PlatformName": "Windows_x64_schannel",
      "TestName": "RPS",
      "MachineName": "22483:TK5-3WP09R0627",
      "TputConfig": null,
      "RpsConfig": {
        "ConnectionCount": 250,
        "RequestSize": 0,
        "ResponseSize": 4096,
        "ParallelRequests": 30
      },
      "HpsConfig": null,
      "Results": [
        802838.0,
        993448.0,
        1090586.0,
        952773.0,
        843480.0
      ]
    },
    {
      "PlatformName": "Windows_x64_schannel",
      "TestName": "RPS",
      "MachineName": "22483:TK5-3WP09R0627",
      "TputConfig": null,
      "RpsConfig": {
        "ConnectionCount": 250,
        "RequestSize": 0,
        "ResponseSize": 0,
        "ParallelRequests": 30
      },
      "HpsConfig": null,
      "Results": [
        863791.0,
        838658.0,
        842895.0,
        810932.0,
        775481.0
      ]
    },
    {
      "PlatformName": "Windows_x64_schannel",
      "TestName": "RPS",
      "MachineName": "22483:TK5-3WP09R0627",
      "TputConfig": null,
      "RpsConfig": {
        "ConnectionCount": 250,
        "RequestSize": 0,
        "ResponseSize": 16384,
        "ParallelRequests": 30
      },
      "HpsConfig": null,
      "Results": [
        340004.0,
        342636.0,
        335346.0,
        339445.0,
        332979.0
      ]
    },
    {
      "PlatformName": "Windows_x64_schannel",
      "TestName": "RPS",
      "MachineName": "22483:TK5-3WP09R0627",
      "TputConfig": null,
      "RpsConfig": {
        "ConnectionCount": 250,
        "RequestSize": 0,
        "ResponseSize": 512,
        "ParallelRequests": 30
      },
      "HpsConfig": null,
      "Results": [
        827782.0,
        902715.0,
        816197.0,
        835227.0,
        867212.0
      ]
    },
    {
      "PlatformName": "Winkernel_x64_schannel",
      "TestName": "RPS",
      "MachineName": "22483:TK5-3WP09R0627",
      "TputConfig": null,
      "RpsConfig": {
        "ConnectionCount": 40,
        "RequestSize": 0,
        "ResponseSize": 4096,
        "ParallelRequests": 30
      },
      "HpsConfig": null,
      "Results": [
        227768.0,
        219243.0,
        222450.0,
        222582.0,
        221917.0
      ]
    },
    {
      "PlatformName": "Winkernel_x64_schannel",
      "TestName": "RPS",
      "MachineName": "22483:TK5-3WP09R0627",
      "TputConfig": null,
      "RpsConfig": {
        "ConnectionCount": 250,
        "RequestSize": 0,
        "ResponseSize": 4096,
        "ParallelRequests": 30
      },
      "HpsConfig": null,
      "Results": [
        1021339.0,
        1052093.0,
        1027146.0,
        1050931.0,
        1041766.0
      ]
    },
    {
      "PlatformName": "Winkernel_x64_schannel",
      "TestName": "RPS",
      "MachineName": "22483:TK5-3WP09R0627",
      "TputConfig": null,
      "RpsConfig": {
        "ConnectionCount": 250,
        "RequestSize": 0,
        "ResponseSize": 0,
        "ParallelRequests": 30
      },
      "HpsConfig": null,
      "Results": [
        942034.0,
        816392.0,
        814834.0,
        886570.0,
        866534.0
      ]
    },
    {
      "PlatformName": "Winkernel_x64_schannel",
      "TestName": "RPS",
      "MachineName": "22483:TK5-3WP09R0627",
      "TputConfig": null,
      "RpsConfig": {
        "ConnectionCount": 250,
        "RequestSize": 0,
        "ResponseSize": 16384,
        "ParallelRequests": 30
      },
      "HpsConfig": null,
      "Results": [
        254264.0,
        279007.0,
        287538.0,
        289694.0,
        253080.0
      ]
    },
    {
      "PlatformName": "Winkernel_x64_schannel",
      "TestName": "RPS",
      "MachineName": "22483:TK5-3WP09R0627",
      "TputConfig": null,
      "RpsConfig": {
        "ConnectionCount": 250,
        "RequestSize": 0,
        "ResponseSize": 512,
        "ParallelRequests": 30
      },
      "HpsConfig": null,
      "Results": [
        1001614.0,
        774742.0,
        930829.0,
        877798.0,
        872887.0
      ]
    },
    {
      "PlatformName": "Windows_x64_schannel",
      "TestName": "TcpThroughput",
      "MachineName": "22483:TK5-3WP09R0627",
      "TputConfig": {
        "Loopback": true,
        "Encryption": false,
        "SendBuffering": false,
        "NumberOfStreams": 1,
        "ServerToClient": true
      },
      "RpsConfig": null,
      "HpsConfig": null,
      "Results": [
        8335382.0,
        8362169.0,
        8371813.0,
        8353782.0,
        8346579.0
      ]
    },
    {
      "PlatformName": "Windows_x64_schannel",
      "TestName": "TcpThroughput",
      "MachineName": "22483:TK5-3WP09R0627",
      "TputConfig": {
        "Loopback": false,
        "Encryption": false,
        "SendBuffering": false,
        "NumberOfStreams": 1,
        "ServerToClient": true
      },
      "RpsConfig": null,
      "HpsConfig": null,
      "Results": [
        11697856.0,
        11679727.0,
        11697000.0,
        11666348.0,
        11638589.0
      ]
    },
    {
      "PlatformName": "Windows_x64_schannel",
      "TestName": "TcpThroughput",
      "MachineName": "22483:TK5-3WP09R0627",
      "TputConfig": {
        "Loopback": true,
        "Encryption": false,
        "SendBuffering": false,
        "NumberOfStreams": 1,
        "ServerToClient": false
      },
      "RpsConfig": null,
      "HpsConfig": null,
      "Results": [
        8103263.0,
        8321713.0,
        8369509.0,
        8384373.0,
        8380570.0
      ]
    },
    {
      "PlatformName": "Windows_x64_schannel",
      "TestName": "TcpThroughput",
      "MachineName": "22483:TK5-3WP09R0627",
      "TputConfig": {
        "Loopback": false,
        "Encryption": false,
        "SendBuffering": false,
        "NumberOfStreams": 1,
        "ServerToClient": false
      },
      "RpsConfig": null,
      "HpsConfig": null,
      "Results": [
        9788201.0,
        12018887.0,
        11662708.0,
        11637506.0,
        11663720.0
      ]
    },
    {
      "PlatformName": "Windows_x64_schannel",
      "TestName": "Throughput",
      "MachineName": "22483:TK5-3WP09R0627",
      "TputConfig": {
        "Loopback": true,
        "Encryption": true,
        "SendBuffering": false,
        "NumberOfStreams": 1,
        "ServerToClient": true
      },
      "RpsConfig": null,
      "HpsConfig": null,
      "Results": [
        7638183.0,
        7740361.0,
        7797521.0,
        7698225.0,
        7704186.0
      ]
    },
    {
      "PlatformName": "Windows_x64_schannel",
      "TestName": "Throughput",
      "MachineName": "22483:TK5-3WP09R0627",
      "TputConfig": {
        "Loopback": false,
        "Encryption": true,
        "SendBuffering": false,
        "NumberOfStreams": 1,
        "ServerToClient": true
      },
      "RpsConfig": null,
      "HpsConfig": null,
      "Results": [
        7793203.0,
        7634334.0,
        7700837.0,
        7741009.0,
        7724639.0
      ]
    },
    {
      "PlatformName": "Windows_x64_schannel",
      "TestName": "Throughput",
      "MachineName": "22483:TK5-3WP09R0627",
      "TputConfig": {
        "Loopback": true,
        "Encryption": false,
        "SendBuffering": false,
        "NumberOfStreams": 1,
        "ServerToClient": true
      },
      "RpsConfig": null,
      "HpsConfig": null,
      "Results": [
        18748842.0,
        19364060.0,
        19248490.0,
        18864921.0,
        19187321.0
      ]
    },
    {
      "PlatformName": "Windows_x64_schannel",
      "TestName": "Throughput",
      "MachineName": "22483:TK5-3WP09R0627",
      "TputConfig": {
        "Loopback": false,
        "Encryption": false,
        "SendBuffering": false,
        "NumberOfStreams": 1,
        "ServerToClient": true
      },
      "RpsConfig": null,
      "HpsConfig": null,
      "Results": [
        18786972.0,
        19357523.0,
        19546831.0,
        19495766.0,
        19476662.0
      ]
    },
    {
      "PlatformName": "Winkernel_x64_schannel",
      "TestName": "Throughput",
      "MachineName": "22483:TK5-3WP09R0627",
      "TputConfig": {
        "Loopback": false,
        "Encryption": true,
        "SendBuffering": false,
        "NumberOfStreams": 1,
        "ServerToClient": true
      },
      "RpsConfig": null,
      "HpsConfig": null,
      "Results": [
        6228041.0,
        6910482.0,
        7028024.0,
        7080122.0,
        7142063.0
      ]
    },
    {
      "PlatformName": "Winkernel_x64_schannel",
      "TestName": "Throughput",
      "MachineName": "22483:TK5-3WP09R0627",
      "TputConfig": {
        "Loopback": false,
        "Encryption": false,
        "SendBuffering": false,
        "NumberOfStreams": 1,
        "ServerToClient": true
      },
      "RpsConfig": null,
      "HpsConfig": null,
      "Results": [
        6100555.0,
        14978776.0,
        18687877.0,
        18891672.0,
        19497191.0
      ]
    },
    {
      "PlatformName": "Windows_x64_schannel",
      "TestName": "Throughput",
      "MachineName": "22483:TK5-3WP09R0627",
      "TputConfig": {
        "Loopback": true,
        "Encryption": true,
        "SendBuffering": false,
        "NumberOfStreams": 1,
        "ServerToClient": false
      },
      "RpsConfig": null,
      "HpsConfig": null,
      "Results": [
        7855312.0,
        7822606.0,
        7723349.0,
        7819250.0,
        7755691.0
      ]
    },
    {
      "PlatformName": "Windows_x64_schannel",
      "TestName": "Throughput",
      "MachineName": "22483:TK5-3WP09R0627",
      "TputConfig": {
        "Loopback": false,
        "Encryption": true,
        "SendBuffering": false,
        "NumberOfStreams": 1,
        "ServerToClient": false
      },
      "RpsConfig": null,
      "HpsConfig": null,
      "Results": [
        7656704.0,
        7715535.0,
        7679356.0,
        7724572.0,
        7763074.0
      ]
    },
    {
      "PlatformName": "Windows_x64_schannel",
      "TestName": "Throughput",
      "MachineName": "22483:TK5-3WP09R0627",
      "TputConfig": {
        "Loopback": true,
        "Encryption": false,
        "SendBuffering": false,
        "NumberOfStreams": 1,
        "ServerToClient": false
      },
      "RpsConfig": null,
      "HpsConfig": null,
      "Results": [
        18333360.0,
        18414277.0,
        18241455.0,
        18547498.0,
        18190562.0
      ]
    },
    {
      "PlatformName": "Windows_x64_schannel",
      "TestName": "Throughput",
      "MachineName": "22483:TK5-3WP09R0627",
      "TputConfig": {
        "Loopback": false,
        "Encryption": false,
        "SendBuffering": false,
        "NumberOfStreams": 1,
        "ServerToClient": false
      },
      "RpsConfig": null,
      "HpsConfig": null,
      "Results": [
        8437572.0,
        8808967.0,
        8690008.0,
        8508981.0,
        8909444.0
      ]
    },
    {
      "PlatformName": "Windows_x64_schannel",
      "TestName": "Throughput",
      "MachineName": "22483:TK5-3WP09R0627",
      "TputConfig": {
        "Loopback": true,
        "Encryption": true,
        "SendBuffering": true,
        "NumberOfStreams": 1,
        "ServerToClient": false
      },
      "RpsConfig": null,
      "HpsConfig": null,
      "Results": [
        7163907.0,
        7315937.0,
        7250974.0,
        7176413.0,
        7115886.0
      ]
    },
    {
      "PlatformName": "Windows_x64_schannel",
      "TestName": "Throughput",
      "MachineName": "22483:TK5-3WP09R0627",
      "TputConfig": {
        "Loopback": false,
        "Encryption": true,
        "SendBuffering": true,
        "NumberOfStreams": 1,
        "ServerToClient": false
      },
      "RpsConfig": null,
      "HpsConfig": null,
      "Results": [
        6900251.0,
        6804074.0,
        6892077.0,
        6030697.0,
        6815880.0
      ]
    },
    {
      "PlatformName": "Winkernel_x64_schannel",
      "TestName": "Throughput",
      "MachineName": "22483:TK5-3WP09R0627",
      "TputConfig": {
        "Loopback": false,
        "Encryption": true,
        "SendBuffering": false,
        "NumberOfStreams": 1,
        "ServerToClient": false
      },
      "RpsConfig": null,
      "HpsConfig": null,
      "Results": [
        5130977.0,
        6571141.0,
        6015691.0,
        6528685.0,
        6560261.0
      ]
    },
    {
      "PlatformName": "Winkernel_x64_schannel",
      "TestName": "Throughput",
      "MachineName": "22483:TK5-3WP09R0627",
      "TputConfig": {
        "Loopback": false,
        "Encryption": false,
        "SendBuffering": false,
        "NumberOfStreams": 1,
        "ServerToClient": false
      },
      "RpsConfig": null,
      "HpsConfig": null,
      "Results": [
        10008776.0,
        10746145.0,
        11126765.0,
        10978914.0,
        11070304.0
      ]
    },
    {
      "PlatformName": "Winkernel_x64_schannel",
      "TestName": "Throughput",
      "MachineName": "22483:TK5-3WP09R0627",
      "TputConfig": {
        "Loopback": false,
        "Encryption": true,
        "SendBuffering": true,
        "NumberOfStreams": 1,
        "ServerToClient": false
      },
      "RpsConfig": null,
      "HpsConfig": null,
      "Results": [
        5459060.0,
        5252414.0,
        5519750.0,
        5362809.0,
        5552542.0
      ]
    }
  ]
}
